[
    {
      "hashtags": [],
      "mediaUrl": "https://scontent-cdg4-2.cdninstagram.com/v/t51.29350-15/341538539_182049214707551_5085415953060103664_n.heic?stp=dst-jpg&_nc_cat=103&ccb=1-7&_nc_sid=8ae9d6&_nc_ohc=mMQOZ7SfmPIAX9-mPdU&_nc_ht=scontent-cdg4-2.cdninstagram.com&edm=ANo9K5cEAAAA&oh=00_AfCesiharNf7Lhclpq_XFRVvfGrpEWbhyAT_KPCsT70bOw&oe=644A38AA",
      "children": [
        {
          "mediaUrl": "https://scontent-cdg4-2.cdninstagram.com/v/t51.29350-15/341538539_182049214707551_5085415953060103664_n.heic?stp=dst-jpg&_nc_cat=103&ccb=1-7&_nc_sid=8ae9d6&_nc_ohc=mMQOZ7SfmPIAX9-mPdU&_nc_ht=scontent-cdg4-2.cdninstagram.com&edm=ANo9K5cEAAAA&oh=00_AfCesiharNf7Lhclpq_XFRVvfGrpEWbhyAT_KPCsT70bOw&oe=644A38AA",
          "mediaType": "IMAGE",
          "id": "18037061674460298"
        },
        {
          "mediaUrl": "https://scontent-cdg4-2.cdninstagram.com/v/t51.29350-15/341735262_183706854505799_8471016125701475844_n.heic?stp=dst-jpg&_nc_cat=103&ccb=1-7&_nc_sid=8ae9d6&_nc_ohc=t4Pc2KO0i_sAX8P7Kr6&_nc_ht=scontent-cdg4-2.cdninstagram.com&edm=ANo9K5cEAAAA&oh=00_AfDs52xY8V04WDrnJFGqmLs7AXVaRRc2L9X34RSelwPcmQ&oe=644BCC54",
          "mediaType": "IMAGE",
          "id": "17996281948832258"
        },
        {
          "mediaUrl": "https://scontent-cdg4-2.cdninstagram.com/v/t51.29350-15/341985260_1265247744413429_34052263668520726_n.heic?stp=dst-jpg&_nc_cat=100&ccb=1-7&_nc_sid=8ae9d6&_nc_ohc=Ln2sgURMASwAX-0ETo7&_nc_ht=scontent-cdg4-2.cdninstagram.com&edm=ANo9K5cEAAAA&oh=00_AfAySozFOwPrlYUZG0F86P03moinvwB-TFtxBDn-VfvgAg&oe=644BC73E",
          "mediaType": "IMAGE",
          "id": "17911950596735561"
        },
        {
          "mediaUrl": "https://scontent-cdg4-2.cdninstagram.com/v/t51.29350-15/342226796_625379628974900_3762993594266549764_n.heic?stp=dst-jpg&_nc_cat=103&ccb=1-7&_nc_sid=8ae9d6&_nc_ohc=gGAtOelro2sAX_-Nb1B&_nc_ht=scontent-cdg4-2.cdninstagram.com&edm=ANo9K5cEAAAA&oh=00_AfDKdGvUgGEwyS7KxF0IjFOc2TOvThBMh85HBmbxoEyHcw&oe=644B5464",
          "mediaType": "IMAGE",
          "id": "17975634971280892"
        },
        {
          "mediaUrl": "https://scontent-cdg4-1.cdninstagram.com/v/t51.29350-15/341800434_723022776218804_1924480578820096608_n.heic?stp=dst-jpg&_nc_cat=108&ccb=1-7&_nc_sid=8ae9d6&_nc_ohc=kN5HLXe65OQAX_6Qumf&_nc_oc=AQnVAjyJCaBT51SJUxpLaK2nsSYD5nhc2yGMxfHvPZcPy_0sJv-E8SLbpwn1sP-TV48&_nc_ht=scontent-cdg4-1.cdninstagram.com&edm=ANo9K5cEAAAA&oh=00_AfC53nxluXTm_f6wNbUlbMh694tuFZOcYSnQQ5w92NzGaQ&oe=644B8106",
          "mediaType": "IMAGE",
          "id": "18045372640399586"
        }
      ],
      "mentions": [],
      "caption": "A veces el cuerpito no acompaña como una quisiera y toca detenerse a darle el tiempo y los cuidados que pide. \n\nGracias a las clientitas que han sabido entenderlo y me han demostrado tanto cariño y preocupación 💖✨\n\nVoy más lentito pero voy igual ✨",
      "mediaType": "CAROUSEL_ALBUM",
      "id": "18005707528650578",
      "permalink": "https://www.instagram.com/p/CrL40E_rgif/",
      "prunedCaption": "A veces el cuerpito no acompaña como una quisiera y toca detenerse a darle el tiempo y los cuidados que pide. \n\nGracias a las clientitas que han sabido entenderlo y me han demostrado tanto cariño y preocupación 💖✨\n\nVoy más lentito pero voy igual ✨",
      "timestamp": "2023-04-18T17:23:31+0000",
      "colorPalette": {
        "vibrantLight": "226,221,130",
        "vibrantDark": "115,91,34",
        "muted": "140,84,156",
        "dominant": "206,172,170",
        "mutedDark": "84,63,41",
        "mutedLight": "217,168,188",
        "vibrant": "174,59,77"
      },
      "dimensions": {
        "width": 1440,
        "height": 1440
      }
    },
    {
      "hashtags": [],
      "mediaUrl": "https://scontent-cdg4-1.cdninstagram.com/v/t51.29350-15/338939370_1703946796722060_3564449757315916111_n.webp?stp=dst-jpg&_nc_cat=106&ccb=1-7&_nc_sid=8ae9d6&_nc_ohc=Kud7QejloEMAX_KBgMP&_nc_ht=scontent-cdg4-1.cdninstagram.com&edm=ANo9K5cEAAAA&oh=00_AfCJeqUxOYEMgpphR67fy7IMVrV7cpWTOok33wm7MfkXbA&oe=644A427B",
      "children": [
        {
          "mediaUrl": "https://scontent-cdg4-1.cdninstagram.com/v/t51.29350-15/338939370_1703946796722060_3564449757315916111_n.webp?stp=dst-jpg&_nc_cat=106&ccb=1-7&_nc_sid=8ae9d6&_nc_ohc=Kud7QejloEMAX_KBgMP&_nc_ht=scontent-cdg4-1.cdninstagram.com&edm=ANo9K5cEAAAA&oh=00_AfCJeqUxOYEMgpphR67fy7IMVrV7cpWTOok33wm7MfkXbA&oe=644A427B",
          "mediaType": "IMAGE",
          "id": "17873256821856312"
        },
        {
          "mediaUrl": "https://scontent-cdg4-1.cdninstagram.com/v/t51.29350-15/339107173_125806377051038_6142127256425837004_n.webp?stp=dst-jpg&_nc_cat=102&ccb=1-7&_nc_sid=8ae9d6&_nc_ohc=bo82EMItXIoAX_T5lBH&_nc_ht=scontent-cdg4-1.cdninstagram.com&edm=ANo9K5cEAAAA&oh=00_AfD6ejyU8czm4nl13dkK0ORvVoFHuDhk5GT4LOotshQ13A&oe=644A5F88",
          "mediaType": "IMAGE",
          "id": "18017917255544402"
        },
        {
          "mediaUrl": "https://scontent-cdg4-1.cdninstagram.com/v/t51.29350-15/338937162_142441385445731_6783620433101681179_n.webp?stp=dst-jpg&_nc_cat=106&ccb=1-7&_nc_sid=8ae9d6&_nc_ohc=vRCjhqS95IkAX92yiSh&_nc_ht=scontent-cdg4-1.cdninstagram.com&edm=ANo9K5cEAAAA&oh=00_AfAzeIYXot75GHt4DTzE1ge6v5dkfwg3nWSI9hI5h8uqkw&oe=644A09EB",
          "mediaType": "IMAGE",
          "id": "18011985454583735"
        },
        {
          "mediaUrl": "https://scontent-cdg4-2.cdninstagram.com/v/t51.29350-15/338946333_1408898066587209_7747463886842325649_n.webp?stp=dst-jpg&_nc_cat=111&ccb=1-7&_nc_sid=8ae9d6&_nc_ohc=aR3DdsuxtlYAX_lmGT5&_nc_ht=scontent-cdg4-2.cdninstagram.com&edm=ANo9K5cEAAAA&oh=00_AfDrx4SfE1o3w7IioZ_2RYLZ7ZoFvYXZUP21-wth371Xsg&oe=644A5530",
          "mediaType": "IMAGE",
          "id": "17980549952045145"
        },
        {
          "mediaUrl": "https://scontent-cdg4-1.cdninstagram.com/v/t51.29350-15/339129929_261455786216914_1581654727024987328_n.webp?stp=dst-jpg&_nc_cat=105&ccb=1-7&_nc_sid=8ae9d6&_nc_ohc=ey7uA4Z1JzsAX_9GOZw&_nc_ht=scontent-cdg4-1.cdninstagram.com&edm=ANo9K5cEAAAA&oh=00_AfBUHtSmnd_Mp5_-whI4SV8PGruJ7A9ZB4Z02YntIKOA2w&oe=644A4831",
          "mediaType": "IMAGE",
          "id": "17992748173857615"
        },
        {
          "mediaUrl": "https://scontent-cdg4-1.cdninstagram.com/v/t51.29350-15/339111100_1473719176492189_2669906270812339013_n.webp?stp=dst-jpg&_nc_cat=102&ccb=1-7&_nc_sid=8ae9d6&_nc_ohc=i0ZOri91yh0AX9WXTZP&_nc_ht=scontent-cdg4-1.cdninstagram.com&edm=ANo9K5cEAAAA&oh=00_AfALUt5xUHkBXdWNhS2jJfBCRKNlQR4gi_7TXqqPlQ1GkA&oe=644B8A4F",
          "mediaType": "IMAGE",
          "id": "17998807795693579"
        }
      ],
      "mentions": [
        "lagrietaoficios",
        "tallerarrastre"
      ],
      "caption": "Fue a la única que alcancé a sacarle fotitos antes de que se largara la lluvia 🤭 \n\nPor estos días me di cuenta de que ya se fue la parka número 100 con cierre engomado y me conmueve mucho pensarlo 💖✨\n\nMuchas gracias a quienes escogen, usan y recomiendan mi trabajo 💖 sobre todo a quienes vuelven una y otra vez 😻🙌\n\nPaso a contarles también que está abierta la agenda de Mayo!\n\n y... Que junto a la Meni, que es la seca detrás de @lagrietaoficios, este Abril tenemos planeadas muchas actividades en @tallerarrastre 🤭\n\nY en Mayo tengo pensado armar un taller para mamis costureras! Les tinca? La idea es que puedan crearle ropita a sus peques y aprendan a usar máquina recta y overlock para eso 😊\n\nAún no están abiertos los cupos para eso perooooo si quieren aclarar dudas, me escriben 💖",
      "mediaType": "CAROUSEL_ALBUM",
      "id": "17997397819750079",
      "permalink": "https://www.instagram.com/p/Cqie6TDLW6j/",
      "prunedCaption": "Fue a la única que alcancé a sacarle fotitos antes de que se largara la lluvia 🤭 \n\nPor estos días me di cuenta de que ya se fue la parka número 100 con cierre engomado y me conmueve mucho pensarlo 💖✨\n\nMuchas gracias a quienes escogen, usan y recomiendan mi trabajo 💖 sobre todo a quienes vuelven una y otra vez 😻🙌\n\nPaso a contarles también que está abierta la agenda de Mayo!\n\n y... Que junto a la Meni, que es la seca detrás de @lagrietaoficios, este Abril tenemos planeadas muchas actividades en @tallerarrastre 🤭\n\nY en Mayo tengo pensado armar un taller para mamis costureras! Les tinca? La idea es que puedan crearle ropita a sus peques y aprendan a usar máquina recta y overlock para eso 😊\n\nAún no están abiertos los cupos para eso perooooo si quieren aclarar dudas, me escriben 💖",
      "timestamp": "2023-04-02T15:28:18+0000",
      "colorPalette": {
        "vibrantLight": "246,148,204",
        "mutedLight": "212,170,175",
        "vibrantDark": "176,17,84",
        "dominant": "216,84,136",
        "vibrant": "208,23,114",
        "muted": "96,160,163",
        "mutedDark": "49,83,92"
      },
      "dimensions": {
        "width": 1440,
        "height": 1440
      }
    },
    {
      "hashtags": [],
      "mediaUrl": "https://scontent-cdg4-1.cdninstagram.com/v/t51.29350-15/337794426_652212633380735_4669966157533413089_n.webp?stp=dst-jpg&_nc_cat=110&ccb=1-7&_nc_sid=8ae9d6&_nc_ohc=ROtSjKiO3MwAX9f1l85&_nc_ht=scontent-cdg4-1.cdninstagram.com&edm=ANo9K5cEAAAA&oh=00_AfCJOJ0JTsWdgt0NP4J7IKolabRNQE1zk-cCtoy9SYf2PQ&oe=644B8217",
      "children": [
        {
          "mediaUrl": "https://scontent-cdg4-1.cdninstagram.com/v/t51.29350-15/337794426_652212633380735_4669966157533413089_n.webp?stp=dst-jpg&_nc_cat=110&ccb=1-7&_nc_sid=8ae9d6&_nc_ohc=ROtSjKiO3MwAX9f1l85&_nc_ht=scontent-cdg4-1.cdninstagram.com&edm=ANo9K5cEAAAA&oh=00_AfCJOJ0JTsWdgt0NP4J7IKolabRNQE1zk-cCtoy9SYf2PQ&oe=644B8217",
          "mediaType": "IMAGE",
          "id": "18000962449660411"
        },
        {
          "mediaUrl": "https://scontent-cdg4-2.cdninstagram.com/v/t51.29350-15/337736925_590677279671296_1679206165891059862_n.webp?stp=dst-jpg&_nc_cat=111&ccb=1-7&_nc_sid=8ae9d6&_nc_ohc=mSCpZQel55MAX-Hjw9o&_nc_ht=scontent-cdg4-2.cdninstagram.com&edm=ANo9K5cEAAAA&oh=00_AfAdrmVazihAA-xgUEy_7vnqo9si_nwiYAnecsk95bsaYg&oe=644A340B",
          "mediaType": "IMAGE",
          "id": "18264527791134165"
        },
        {
          "mediaUrl": "https://scontent-cdg4-1.cdninstagram.com/v/t51.29350-15/337740581_616509703227465_9204330415531915423_n.webp?stp=dst-jpg&_nc_cat=102&ccb=1-7&_nc_sid=8ae9d6&_nc_ohc=YdJc19W0jRoAX_B4M6Z&_nc_ht=scontent-cdg4-1.cdninstagram.com&edm=ANo9K5cEAAAA&oh=00_AfD_CqGoyPQTGd2zgk2swEdgKCSheCCFBhbvwVBxMq18wQ&oe=644BB3DB",
          "mediaType": "IMAGE",
          "id": "17980176131072947"
        },
        {
          "mediaUrl": "https://scontent-cdg4-2.cdninstagram.com/v/t51.29350-15/338018127_597543235603901_2944291694587163370_n.webp?stp=dst-jpg&_nc_cat=111&ccb=1-7&_nc_sid=8ae9d6&_nc_ohc=9U3nODzMBCMAX_AlQps&_nc_oc=AQnmuEptDTnfLhG2joo_8sY5dworaoy0nuZ4klWMtrBMlAWEqyVlGeOIBgEd7ujludA&_nc_ht=scontent-cdg4-2.cdninstagram.com&edm=ANo9K5cEAAAA&oh=00_AfB7WpNRSgZbxbY_-yxJAQJzZjRgjRPfTuMj8gi-MzIPfQ&oe=644B18F8",
          "mediaType": "IMAGE",
          "id": "17952107072347418"
        },
        {
          "mediaUrl": "https://scontent-cdg4-2.cdninstagram.com/v/t51.29350-15/338303551_208156491818446_1036384413420279258_n.webp?stp=dst-jpg&_nc_cat=107&ccb=1-7&_nc_sid=8ae9d6&_nc_ohc=EUnzOe4vx4oAX8VF2Pr&_nc_ht=scontent-cdg4-2.cdninstagram.com&edm=ANo9K5cEAAAA&oh=00_AfCYJ_7wMA_rzd3FF2RZneWkPqHMvXxp4uxfVCaB36cGPA&oe=644AE62A",
          "mediaType": "IMAGE",
          "id": "18155739739303499"
        },
        {
          "mediaUrl": "https://scontent-cdg4-2.cdninstagram.com/v/t51.29350-15/337908973_742911747308075_5628382650127698732_n.webp?stp=dst-jpg&_nc_cat=109&ccb=1-7&_nc_sid=8ae9d6&_nc_ohc=mqX6PiDwiDEAX9bCUiC&_nc_ht=scontent-cdg4-2.cdninstagram.com&edm=ANo9K5cEAAAA&oh=00_AfC2YY21Z0zLNBeuZf7B4lu-TqCiwA4HJHRBLqZX2huhkQ&oe=644A996E",
          "mediaType": "IMAGE",
          "id": "17964280619173059"
        }
      ],
      "mentions": [],
      "caption": "Hoy aprovechamos que estábamos en el campo para sacar fotitos al nuevo modelo de polerón que trabajaremos este año 😻💖\n\nLe estamos buscando nombre, así que si tienes una idea, siempre es bienvenida! Sortearemos un poleroncito en talla infantil entre quienes se atrevan 🤭\n\nEsta semana terminamos de entregar los pedidos de Marzo, así que atentxs para coordinar :)\n\nQue tengan una hermosa semana! Ya se siente el otoño y nos encanta ✨🍁🍂",
      "mediaType": "CAROUSEL_ALBUM",
      "id": "17884521038767981",
      "permalink": "https://www.instagram.com/p/CqReVzNN_QR/",
      "prunedCaption": "Hoy aprovechamos que estábamos en el campo para sacar fotitos al nuevo modelo de polerón que trabajaremos este año 😻💖\n\nLe estamos buscando nombre, así que si tienes una idea, siempre es bienvenida! Sortearemos un poleroncito en talla infantil entre quienes se atrevan 🤭\n\nEsta semana terminamos de entregar los pedidos de Marzo, así que atentxs para coordinar :)\n\nQue tengan una hermosa semana! Ya se siente el otoño y nos encanta ✨🍁🍂",
      "timestamp": "2023-03-27T00:56:14+0000",
      "colorPalette": {
        "vibrant": "116,164,196",
        "vibrantLight": "155,182,210",
        "mutedLight": "208,175,163",
        "muted": "135,116,92",
        "dominant": "203,176,196",
        "mutedDark": "98,82,47",
        "vibrantDark": "93,75,28"
      },
      "dimensions": {
        "height": 1440,
        "width": 1440
      }
    },
    {
      "hashtags": [],
      "mediaUrl": "https://scontent-cdg4-1.cdninstagram.com/v/t51.29350-15/332068003_164596493018141_9212876071955769873_n.webp?stp=dst-jpg&_nc_cat=102&ccb=1-7&_nc_sid=8ae9d6&_nc_ohc=2OWs4Pt2VtIAX9OYHPr&_nc_ht=scontent-cdg4-1.cdninstagram.com&edm=ANo9K5cEAAAA&oh=00_AfBKKuTa-HjT-YN5OretKWF8iBszhclYQeG3oCcZa04t4A&oe=644A72CD",
      "children": [
        {
          "mediaUrl": "https://scontent-cdg4-1.cdninstagram.com/v/t51.29350-15/332068003_164596493018141_9212876071955769873_n.webp?stp=dst-jpg&_nc_cat=102&ccb=1-7&_nc_sid=8ae9d6&_nc_ohc=2OWs4Pt2VtIAX9OYHPr&_nc_ht=scontent-cdg4-1.cdninstagram.com&edm=ANo9K5cEAAAA&oh=00_AfBKKuTa-HjT-YN5OretKWF8iBszhclYQeG3oCcZa04t4A&oe=644A72CD",
          "mediaType": "IMAGE",
          "id": "17975251741930941"
        },
        {
          "mediaUrl": "https://scontent-cdg4-1.cdninstagram.com/v/t51.29350-15/332006144_164320506362771_1396677088797381844_n.webp?stp=dst-jpg&_nc_cat=104&ccb=1-7&_nc_sid=8ae9d6&_nc_ohc=KBLxvPONzs4AX_Wrcw9&_nc_ht=scontent-cdg4-1.cdninstagram.com&edm=ANo9K5cEAAAA&oh=00_AfDDzspRwfq5qwBp7vVj9j7fXmkEE7QHnTEu4ToTEwjL0Q&oe=644A7EA7",
          "mediaType": "IMAGE",
          "id": "18348716923043307"
        },
        {
          "mediaUrl": "https://scontent-cdg4-1.cdninstagram.com/v/t51.29350-15/332155920_5915906845142231_5931319449161490276_n.webp?stp=dst-jpg&_nc_cat=108&ccb=1-7&_nc_sid=8ae9d6&_nc_ohc=fLMDbwR0oR4AX98VSkN&_nc_ht=scontent-cdg4-1.cdninstagram.com&edm=ANo9K5cEAAAA&oh=00_AfDvWK_LdZy3ESRkCuKpMcUxeqH46KR_TljU8pVBfmyfug&oe=644A4219",
          "mediaType": "IMAGE",
          "id": "17953929731303552"
        },
        {
          "mediaUrl": "https://scontent-cdg4-1.cdninstagram.com/v/t51.29350-15/332004913_232066715886007_6908236891691620490_n.webp?stp=dst-jpg&_nc_cat=105&ccb=1-7&_nc_sid=8ae9d6&_nc_ohc=FXofoXWlAP8AX-53BUP&_nc_ht=scontent-cdg4-1.cdninstagram.com&edm=ANo9K5cEAAAA&oh=00_AfCMHhhL_RlYPcRer2LhuSK-AT9jkV27vwJcZ6i26-UvdA&oe=644A69FA",
          "mediaType": "IMAGE",
          "id": "17967188405184557"
        },
        {
          "mediaUrl": "https://scontent-cdg4-2.cdninstagram.com/v/t51.29350-15/332666488_5653444694764926_8343194675416786912_n.webp?stp=dst-jpg&_nc_cat=111&ccb=1-7&_nc_sid=8ae9d6&_nc_ohc=4My4SJX_hxcAX8utkQm&_nc_ht=scontent-cdg4-2.cdninstagram.com&edm=ANo9K5cEAAAA&oh=00_AfBktmkf5-UX9yHj8cMiZY0Ro5TYoiZvjuiUqKe8DSILVQ&oe=644B7C4C",
          "mediaType": "IMAGE",
          "id": "17933346896630763"
        }
      ],
      "mentions": [],
      "caption": "✨ Agenda de parkas abierta ✨\n\nVolvemos con ganas de prepararnos para nuestra estación favorita 😻 así es que hoy comenzamos a recibir pedidos de parkas 💖\n\nRecuerda que las parkitas tienen:\n- Tela impermeable\n- Cierre engomado\n- Forro de polar\n- Colores personalizados\n- Puñitos de algodón \n\nY sobre todo.. recuerda que encuentras los modelos en historias destacadas 🤭\n\nEste año trabajaremos con agenda mensual. Abriremos pedidos sólo para 5 parkitas y la fecha de entrega es durante el mes siguiente. A medida que agendes podremos ir conversándolo mejor ☺️\n\nÁnimo con los preparativos para regresar al colegio y sus rutinas 🖖se viene un año intenso dicen jaja",
      "mediaType": "CAROUSEL_ALBUM",
      "id": "17927727074548959",
      "permalink": "https://www.instagram.com/p/Co8g2VYNlN3/",
      "prunedCaption": "✨ Agenda de parkas abierta ✨\n\nVolvemos con ganas de prepararnos para nuestra estación favorita 😻 así es que hoy comenzamos a recibir pedidos de parkas 💖\n\nRecuerda que las parkitas tienen:\n- Tela impermeable\n- Cierre engomado\n- Forro de polar\n- Colores personalizados\n- Puñitos de algodón \n\nY sobre todo.. recuerda que encuentras los modelos en historias destacadas 🤭\n\nEste año trabajaremos con agenda mensual. Abriremos pedidos sólo para 5 parkitas y la fecha de entrega es durante el mes siguiente. A medida que agendes podremos ir conversándolo mejor ☺️\n\nÁnimo con los preparativos para regresar al colegio y sus rutinas 🖖se viene un año intenso dicen jaja",
      "timestamp": "2023-02-22T01:02:42+0000",
      "colorPalette": {
        "vibrantLight": "252,205,31",
        "mutedLight": "150,119,2",
        "dominant": "50,71,59",
        "muted": "135,113,81",
        "vibrantDark": "11,160,143",
        "mutedDark": "54,81,82",
        "vibrant": "251,188,21"
      },
      "dimensions": {
        "width": 1440,
        "height": 1440
      }
    },
    {
      "hashtags": [],
      "mediaUrl": "https://scontent-cdg4-2.cdninstagram.com/o1/v/t16/f1/m82/6646010A942AF4DB8525F1733DE53899_video_dashinit.mp4?efg=eyJ2ZW5jb2RlX3RhZyI6InZ0c192b2RfdXJsZ2VuLjcyMC5jbGlwcyJ9&_nc_ht=scontent-cdg4-2.cdninstagram.com&_nc_cat=105&vs=2900707296730395_1344517806&_nc_vs=HBksFQIYT2lnX3hwdl9yZWVsc19wZXJtYW5lbnRfcHJvZC82NjQ2MDEwQTk0MkFGNERCODUyNUYxNzMzREU1Mzg5OV92aWRlb19kYXNoaW5pdC5tcDQVAALIAQAVABgkR0pCalhSTVpKZDFqaXJBTEFMaTk0b1BDVUhGY2JxX0VBQUFGFQICyAEAKAAYABsBiAd1c2Vfb2lsATEVAAAm5sW1nZDr7T8VAigCQzMsF0Aktsi0OVgQGBJkYXNoX2Jhc2VsaW5lXzFfdjERAHUAAA%3D%3D&ccb=9-4&oh=00_AfD0gwCzutUN9ODFronOvkOtJiUpeFMvB5PMCV0296Pffg&oe=6447CB46&_nc_sid=ea0b6e&_nc_rid=616a571a46",
      "mentions": [],
      "caption": "Muchas gracias por el recibimiento que tuvieron los productos en oferta 🤭🔥\n\nYa van quedando poquitas cosas, y me alegra mucho ver que hay clientitxs que siempre vuelven ✨💖\n\nRecuerden que pueden pedir fotitos y medidas por mensajes, que pueden venir a ver/probar al taller en Baquedano 628 pero que también hago envios de ser necesario! \n\nY volvemos a finales de Febrero con las pilas y el corazoncito recargados 🔥🫀",
      "mediaType": "VIDEO",
      "id": "18339525400020161",
      "permalink": "https://www.instagram.com/reel/CnPpz8fo5bh/",
      "isReel": true,
      "prunedCaption": "Muchas gracias por el recibimiento que tuvieron los productos en oferta 🤭🔥\n\nYa van quedando poquitas cosas, y me alegra mucho ver que hay clientitxs que siempre vuelven ✨💖\n\nRecuerden que pueden pedir fotitos y medidas por mensajes, que pueden venir a ver/probar al taller en Baquedano 628 pero que también hago envios de ser necesario! \n\nY volvemos a finales de Febrero con las pilas y el corazoncito recargados 🔥🫀",
      "thumbnailUrl": "https://scontent-cdg4-1.cdninstagram.com/v/t51.29350-15/324698968_178288718167511_1720715286176424972_n.jpg?_nc_cat=105&ccb=1-7&_nc_sid=8ae9d6&_nc_ohc=3G3L-esjuRgAX8ePJA2&_nc_ht=scontent-cdg4-1.cdninstagram.com&edm=ANo9K5cEAAAA&oh=00_AfBazTgJwhBmQGFRFhr92ppygYNRdCRN9Pale4O16q2OpQ&oe=6449FEA1",
      "timestamp": "2023-01-10T18:27:08+0000",
      "colorPalette": {
        "muted": "161,128,89",
        "vibrant": "175,17,23",
        "dominant": "151,34,28",
        "mutedLight": "129,66,23",
        "vibrantDark": "151,11,11",
        "vibrantLight": "240,199,171",
        "mutedDark": "146,101,72"
      },
      "dimensions": {
        "height": 1920,
        "width": 1080
      }
    },
    {
      "mediaUrl": "https://scontent-cdg4-2.cdninstagram.com/v/t51.29350-15/318099976_814143132990401_8495900118246429984_n.webp?stp=dst-jpg&_nc_cat=100&ccb=1-7&_nc_sid=8ae9d6&_nc_ohc=3EAvjqAVtfwAX_Uik9g&_nc_oc=AQmLuMgFp4kvT1x1yfUs9OgMmLtSZJ2Ojyqv0zKzvRG4uItQPCjh6KhkZniTjZ-6hVM&_nc_ht=scontent-cdg4-2.cdninstagram.com&edm=ANo9K5cEAAAA&oh=00_AfBdGrLwYHy8w-X7w9SrRaFJ8QzsuOLvM-MMxIch-hDe5Q&oe=644B891F",
      "hashtags": [
        "ropainfantil",
        "diseñoinfantil",
        "diseñoindependiente",
        "diseñochileno",
        "hechoenchile",
        "hechoamano",
        "handmade",
        "hechoenvaldivia",
        "valdiviachile"
      ],
      "children": [
        {
          "mediaUrl": "https://scontent-cdg4-2.cdninstagram.com/v/t51.29350-15/318099976_814143132990401_8495900118246429984_n.webp?stp=dst-jpg&_nc_cat=100&ccb=1-7&_nc_sid=8ae9d6&_nc_ohc=3EAvjqAVtfwAX_Uik9g&_nc_oc=AQmLuMgFp4kvT1x1yfUs9OgMmLtSZJ2Ojyqv0zKzvRG4uItQPCjh6KhkZniTjZ-6hVM&_nc_ht=scontent-cdg4-2.cdninstagram.com&edm=ANo9K5cEAAAA&oh=00_AfBdGrLwYHy8w-X7w9SrRaFJ8QzsuOLvM-MMxIch-hDe5Q&oe=644B891F",
          "mediaType": "IMAGE",
          "id": "17960681765126362"
        },
        {
          "mediaUrl": "https://scontent-cdg4-2.cdninstagram.com/v/t51.29350-15/318096237_1181287162594962_3131129621005479036_n.webp?stp=dst-jpg&_nc_cat=101&ccb=1-7&_nc_sid=8ae9d6&_nc_ohc=Sw7CseIu3YYAX-nctVY&_nc_ht=scontent-cdg4-2.cdninstagram.com&edm=ANo9K5cEAAAA&oh=00_AfD44Pv36r3szdlQvUM9i9m-KOWTY7FXAJ560GuRfIQwFQ&oe=644BA59E",
          "mediaType": "IMAGE",
          "id": "18238583203159466"
        },
        {
          "mediaUrl": "https://scontent-cdg4-1.cdninstagram.com/v/t51.29350-15/318234435_1591291821281341_7234544833036726866_n.webp?stp=dst-jpg&_nc_cat=104&ccb=1-7&_nc_sid=8ae9d6&_nc_ohc=47tgBxim2HQAX8NaDgj&_nc_ht=scontent-cdg4-1.cdninstagram.com&edm=ANo9K5cEAAAA&oh=00_AfD6taQIW3obC1QU2urIkQu--ozjUVKSJ64FSDbt4bukbQ&oe=644A36CB",
          "mediaType": "IMAGE",
          "id": "17903753495692035"
        },
        {
          "mediaUrl": "https://scontent-cdg4-1.cdninstagram.com/v/t51.29350-15/318016093_182103297742978_283624481773958147_n.webp?stp=dst-jpg&_nc_cat=106&ccb=1-7&_nc_sid=8ae9d6&_nc_ohc=OVxjYVyqWw8AX8-1DWq&_nc_ht=scontent-cdg4-1.cdninstagram.com&edm=ANo9K5cEAAAA&oh=00_AfCRoA_k4BbcaE64OsJXs1jf7tEU01-B3UYTYML1UH18QQ&oe=644BD9FD",
          "mediaType": "IMAGE",
          "id": "17969631622982419"
        }
      ],
      "mentions": [
        "cegecis",
        "buenafibracolectiva"
      ],
      "caption": "✨Agenda abierta para navidad ✨\n\nSerán poquitos cupos este año porque priorizaremos la salud. Hemos vivido navidades muy locas por trabajólica 😜\n\nTambién les cuento que este sábado estaremos en una actividad organizada por @cegecis junto a las @buenafibracolectiva 😻 Les comparto por historias la información 🤭\n\nY el 17 se viene otra fecha importante en un lugar muy especial, así que agéndalo 💖\n\nLes dejo fotitos de algunos cortavientos que se han ido 😻✨\n\n#ropainfantil #diseñoinfantil #diseñoindependiente #diseñochileno #hechoenchile #hechoamano #handmade #hechoenvaldivia #valdiviachile",
      "mediaType": "CAROUSEL_ALBUM",
      "id": "17896468277709288",
      "permalink": "https://www.instagram.com/p/ClzjjzftCCD/",
      "prunedCaption": "✨Agenda abierta para navidad ✨\n\nSerán poquitos cupos este año porque priorizaremos la salud. Hemos vivido navidades muy locas por trabajólica 😜\n\nTambién les cuento que este sábado estaremos en una actividad organizada por @cegecis junto a las @buenafibracolectiva 😻 Les comparto por historias la información 🤭\n\nY el 17 se viene otra fecha importante en un lugar muy especial, así que agéndalo 💖\n\nLes dejo fotitos de algunos cortavientos que se han ido 😻✨",
      "timestamp": "2022-12-05T23:59:03+0000",
      "colorPalette": {
        "mutedLight": "191,157,146",
        "vibrant": "4,171,147",
        "vibrantLight": "246,181,169",
        "vibrantDark": "7,134,109",
        "mutedDark": "75,82,39",
        "muted": "183,99,99",
        "dominant": "211,156,144"
      },
      "dimensions": {
        "width": 1440,
        "height": 1440
      }
    }
  ]